blacksheep_request_logger/__init__.py
blacksheep_request_logger/middleware.py
blacksheep_request_logger-0.1.0.dist-info/METADATA
blacksheep_request_logger-0.1.0.dist-info/WHEEL
blacksheep_request_logger-0.1.0.dist-info/licenses/LICENSE
blacksheep_request_logger-0.1.0.dist-info/RECORD
